{
  "@context": {
    "ontolex": "http://www.w3.org/ns/lemon/ontolex#",
    "lexicog": "http://www.w3.org/ns/lemon/lexicog#",
    "decomp": "http://www.w3.org/ns/lemon/decomp#",
    "frac": "http://www.w3.org/ns/lemon/frac#",
    "prov": "http://www.w3.org/ns/prov#",
    "dct": "http://purl.org/dc/terms/",
    "rdf": "http://www.w3.org/1999/02/22-rdf-syntax-ns#",
    "rdfs": "http://www.w3.org/2000/01/rdf-schema#",
    "skos": "http://www.w3.org/2004/02/skos/core#",
    "csl": "https://sanskrit-lexicon.github.io/csl-standards/ns#"
  },
  "@id": "https://sanskrit-lexicon.github.io/csl-standards/id/case/mw-pwg-pwk%3Aakza",
  "@graph": [
    {
      "@id": "https://sanskrit-lexicon.github.io/csl-standards/id/case/mw-pwg-pwk%3Aakza",
      "@type": [
        "ontolex:LexicalEntry"
      ],
      "ontolex:canonicalForm": {
        "@id": "https://sanskrit-lexicon.github.io/csl-standards/id/case/mw-pwg-pwk%3Aakza#form-canonical"
      },
      "ontolex:sense": [
        {
          "@id": "https://sanskrit-lexicon.github.io/csl-standards/id/case/mw-pwg-pwk%3Aakza#sense-mw-1"
        },
        {
          "@id": "https://sanskrit-lexicon.github.io/csl-standards/id/case/mw-pwg-pwk%3Aakza#sense-pwg-1"
        },
        {
          "@id": "https://sanskrit-lexicon.github.io/csl-standards/id/case/mw-pwg-pwk%3Aakza#sense-pwg-2"
        },
        {
          "@id": "https://sanskrit-lexicon.github.io/csl-standards/id/case/mw-pwg-pwk%3Aakza#sense-pwg-3"
        },
        {
          "@id": "https://sanskrit-lexicon.github.io/csl-standards/id/case/mw-pwg-pwk%3Aakza#sense-pwg-4"
        },
        {
          "@id": "https://sanskrit-lexicon.github.io/csl-standards/id/case/mw-pwg-pwk%3Aakza#sense-pwg-5"
        },
        {
          "@id": "https://sanskrit-lexicon.github.io/csl-standards/id/case/mw-pwg-pwk%3Aakza#sense-pwg-6"
        },
        {
          "@id": "https://sanskrit-lexicon.github.io/csl-standards/id/case/mw-pwg-pwk%3Aakza#sense-pwk-1"
        },
        {
          "@id": "https://sanskrit-lexicon.github.io/csl-standards/id/case/mw-pwg-pwk%3Aakza#sense-pwk-2"
        },
        {
          "@id": "https://sanskrit-lexicon.github.io/csl-standards/id/case/mw-pwg-pwk%3Aakza#sense-pwk-3"
        },
        {
          "@id": "https://sanskrit-lexicon.github.io/csl-standards/id/case/mw-pwg-pwk%3Aakza#sense-pwk-4"
        },
        {
          "@id": "https://sanskrit-lexicon.github.io/csl-standards/id/case/mw-pwg-pwk%3Aakza#sense-gra-1"
        },
        {
          "@id": "https://sanskrit-lexicon.github.io/csl-standards/id/case/mw-pwg-pwk%3Aakza#sense-fri-1"
        }
      ],
      "frac:attestation": [
        {
          "@id": "https://sanskrit-lexicon.github.io/csl-standards/id/case/mw-pwg-pwk%3Aakza#attestation-1"
        },
        {
          "@id": "https://sanskrit-lexicon.github.io/csl-standards/id/case/mw-pwg-pwk%3Aakza#attestation-2"
        },
        {
          "@id": "https://sanskrit-lexicon.github.io/csl-standards/id/case/mw-pwg-pwk%3Aakza#attestation-3"
        },
        {
          "@id": "https://sanskrit-lexicon.github.io/csl-standards/id/case/mw-pwg-pwk%3Aakza#attestation-4"
        },
        {
          "@id": "https://sanskrit-lexicon.github.io/csl-standards/id/case/mw-pwg-pwk%3Aakza#attestation-5"
        },
        {
          "@id": "https://sanskrit-lexicon.github.io/csl-standards/id/case/mw-pwg-pwk%3Aakza#attestation-6"
        },
        {
          "@id": "https://sanskrit-lexicon.github.io/csl-standards/id/case/mw-pwg-pwk%3Aakza#attestation-7"
        },
        {
          "@id": "https://sanskrit-lexicon.github.io/csl-standards/id/case/mw-pwg-pwk%3Aakza#attestation-8"
        },
        {
          "@id": "https://sanskrit-lexicon.github.io/csl-standards/id/case/mw-pwg-pwk%3Aakza#attestation-9"
        },
        {
          "@id": "https://sanskrit-lexicon.github.io/csl-standards/id/case/mw-pwg-pwk%3Aakza#attestation-10"
        },
        {
          "@id": "https://sanskrit-lexicon.github.io/csl-standards/id/case/mw-pwg-pwk%3Aakza#attestation-11"
        },
        {
          "@id": "https://sanskrit-lexicon.github.io/csl-standards/id/case/mw-pwg-pwk%3Aakza#attestation-12"
        },
        {
          "@id": "https://sanskrit-lexicon.github.io/csl-standards/id/case/mw-pwg-pwk%3Aakza#attestation-13"
        },
        {
          "@id": "https://sanskrit-lexicon.github.io/csl-standards/id/case/mw-pwg-pwk%3Aakza#attestation-14"
        },
        {
          "@id": "https://sanskrit-lexicon.github.io/csl-standards/id/case/mw-pwg-pwk%3Aakza#attestation-15"
        },
        {
          "@id": "https://sanskrit-lexicon.github.io/csl-standards/id/case/mw-pwg-pwk%3Aakza#attestation-16"
        },
        {
          "@id": "https://sanskrit-lexicon.github.io/csl-standards/id/case/mw-pwg-pwk%3Aakza#attestation-17"
        },
        {
          "@id": "https://sanskrit-lexicon.github.io/csl-standards/id/case/mw-pwg-pwk%3Aakza#attestation-18"
        },
        {
          "@id": "https://sanskrit-lexicon.github.io/csl-standards/id/case/mw-pwg-pwk%3Aakza#attestation-19"
        },
        {
          "@id": "https://sanskrit-lexicon.github.io/csl-standards/id/case/mw-pwg-pwk%3Aakza#attestation-20"
        },
        {
          "@id": "https://sanskrit-lexicon.github.io/csl-standards/id/case/mw-pwg-pwk%3Aakza#attestation-21"
        },
        {
          "@id": "https://sanskrit-lexicon.github.io/csl-standards/id/case/mw-pwg-pwk%3Aakza#attestation-22"
        },
        {
          "@id": "https://sanskrit-lexicon.github.io/csl-standards/id/case/mw-pwg-pwk%3Aakza#attestation-23"
        },
        {
          "@id": "https://sanskrit-lexicon.github.io/csl-standards/id/case/mw-pwg-pwk%3Aakza#attestation-24"
        },
        {
          "@id": "https://sanskrit-lexicon.github.io/csl-standards/id/case/mw-pwg-pwk%3Aakza#attestation-25"
        },
        {
          "@id": "https://sanskrit-lexicon.github.io/csl-standards/id/case/mw-pwg-pwk%3Aakza#attestation-26"
        },
        {
          "@id": "https://sanskrit-lexicon.github.io/csl-standards/id/case/mw-pwg-pwk%3Aakza#attestation-27"
        },
        {
          "@id": "https://sanskrit-lexicon.github.io/csl-standards/id/case/mw-pwg-pwk%3Aakza#attestation-28"
        },
        {
          "@id": "https://sanskrit-lexicon.github.io/csl-standards/id/case/mw-pwg-pwk%3Aakza#attestation-29"
        },
        {
          "@id": "https://sanskrit-lexicon.github.io/csl-standards/id/case/mw-pwg-pwk%3Aakza#attestation-30"
        },
        {
          "@id": "https://sanskrit-lexicon.github.io/csl-standards/id/case/mw-pwg-pwk%3Aakza#attestation-31"
        },
        {
          "@id": "https://sanskrit-lexicon.github.io/csl-standards/id/case/mw-pwg-pwk%3Aakza#attestation-32"
        },
        {
          "@id": "https://sanskrit-lexicon.github.io/csl-standards/id/case/mw-pwg-pwk%3Aakza#attestation-33"
        },
        {
          "@id": "https://sanskrit-lexicon.github.io/csl-standards/id/case/mw-pwg-pwk%3Aakza#attestation-34"
        }
      ],
      "csl:sourceRecord": [
        {
          "@id": "https://sanskrit-lexicon.github.io/csl-standards/id/case/mw-pwg-pwk%3Aakza#record-mw"
        },
        {
          "@id": "https://sanskrit-lexicon.github.io/csl-standards/id/case/mw-pwg-pwk%3Aakza#record-pwg"
        },
        {
          "@id": "https://sanskrit-lexicon.github.io/csl-standards/id/case/mw-pwg-pwk%3Aakza#record-pwk"
        },
        {
          "@id": "https://sanskrit-lexicon.github.io/csl-standards/id/case/mw-pwg-pwk%3Aakza#record-gra"
        },
        {
          "@id": "https://sanskrit-lexicon.github.io/csl-standards/id/case/mw-pwg-pwk%3Aakza#record-fri"
        },
        {
          "@id": "https://sanskrit-lexicon.github.io/csl-standards/id/case/mw-pwg-pwk%3Aakza#record-ben"
        }
      ],
      "csl:caseId": "mw-pwg-pwk:akza",
      "csl:key": "akza",
      "csl:entryType": "lemma",
      "csl:phenomenon": [
        "hedge",
        "tri-dict",
        "pwg-rich",
        "pwk-abridged",
        "homophone"
      ],
      "csl:profileVersion": "ontolex-frac-profile-v0.1",
      "csl:reviewStatus": "full-machine-review",
      "csl:validationScope": "full-ontolex-shacl-profile"
    },
    {
      "@id": "https://sanskrit-lexicon.github.io/csl-standards/id/case/mw-pwg-pwk%3Aakza#form-canonical",
      "@type": "ontolex:Form",
      "ontolex:writtenRep": {
        "@value": "akza",
        "@language": "sa-Latn-x-SLP1"
      }
    },
    {
      "@id": "https://sanskrit-lexicon.github.io/csl-standards/id/case/mw-pwg-pwk%3Aakza#resource-mw",
      "@type": "lexicog:LexicographicResource",
      "dct:source": "Monier-Williams 1899",
      "csl:dictionary": "mw",
      "lexicog:entry": {
        "@id": "https://sanskrit-lexicon.github.io/csl-standards/id/case/mw-pwg-pwk%3Aakza#lexentry-mw"
      }
    },
    {
      "@id": "https://sanskrit-lexicon.github.io/csl-standards/id/case/mw-pwg-pwk%3Aakza#resource-pwg",
      "@type": "lexicog:LexicographicResource",
      "dct:source": "Boehtlingk-Roth PWG",
      "csl:dictionary": "pwg",
      "lexicog:entry": {
        "@id": "https://sanskrit-lexicon.github.io/csl-standards/id/case/mw-pwg-pwk%3Aakza#lexentry-pwg"
      }
    },
    {
      "@id": "https://sanskrit-lexicon.github.io/csl-standards/id/case/mw-pwg-pwk%3Aakza#resource-pwk",
      "@type": "lexicog:LexicographicResource",
      "dct:source": "Boehtlingk PWK",
      "csl:dictionary": "pwk",
      "lexicog:entry": {
        "@id": "https://sanskrit-lexicon.github.io/csl-standards/id/case/mw-pwg-pwk%3Aakza#lexentry-pwk"
      }
    },
    {
      "@id": "https://sanskrit-lexicon.github.io/csl-standards/id/case/mw-pwg-pwk%3Aakza#resource-gra",
      "@type": "lexicog:LexicographicResource",
      "dct:source": "Grassmann Wörterbuch zum Rig-Veda",
      "csl:dictionary": "gra",
      "lexicog:entry": {
        "@id": "https://sanskrit-lexicon.github.io/csl-standards/id/case/mw-pwg-pwk%3Aakza#lexentry-gra"
      }
    },
    {
      "@id": "https://sanskrit-lexicon.github.io/csl-standards/id/case/mw-pwg-pwk%3Aakza#resource-fri",
      "@type": "lexicog:LexicographicResource",
      "dct:source": "Frish Sanskrit Reader (Cologne 2015)",
      "csl:dictionary": "fri",
      "lexicog:entry": {
        "@id": "https://sanskrit-lexicon.github.io/csl-standards/id/case/mw-pwg-pwk%3Aakza#lexentry-fri"
      }
    },
    {
      "@id": "https://sanskrit-lexicon.github.io/csl-standards/id/case/mw-pwg-pwk%3Aakza#lexentry-mw",
      "@type": "lexicog:Entry",
      "lexicog:describes": {
        "@id": "https://sanskrit-lexicon.github.io/csl-standards/id/case/mw-pwg-pwk%3Aakza"
      },
      "lexicog:component": [
        {
          "@id": "https://sanskrit-lexicon.github.io/csl-standards/id/case/mw-pwg-pwk%3Aakza#sense-mw-1"
        }
      ]
    },
    {
      "@id": "https://sanskrit-lexicon.github.io/csl-standards/id/case/mw-pwg-pwk%3Aakza#lexentry-pwg",
      "@type": "lexicog:Entry",
      "lexicog:describes": {
        "@id": "https://sanskrit-lexicon.github.io/csl-standards/id/case/mw-pwg-pwk%3Aakza"
      },
      "lexicog:component": [
        {
          "@id": "https://sanskrit-lexicon.github.io/csl-standards/id/case/mw-pwg-pwk%3Aakza#sense-pwg-1"
        },
        {
          "@id": "https://sanskrit-lexicon.github.io/csl-standards/id/case/mw-pwg-pwk%3Aakza#sense-pwg-2"
        },
        {
          "@id": "https://sanskrit-lexicon.github.io/csl-standards/id/case/mw-pwg-pwk%3Aakza#sense-pwg-3"
        },
        {
          "@id": "https://sanskrit-lexicon.github.io/csl-standards/id/case/mw-pwg-pwk%3Aakza#sense-pwg-4"
        },
        {
          "@id": "https://sanskrit-lexicon.github.io/csl-standards/id/case/mw-pwg-pwk%3Aakza#sense-pwg-5"
        },
        {
          "@id": "https://sanskrit-lexicon.github.io/csl-standards/id/case/mw-pwg-pwk%3Aakza#sense-pwg-6"
        }
      ]
    },
    {
      "@id": "https://sanskrit-lexicon.github.io/csl-standards/id/case/mw-pwg-pwk%3Aakza#lexentry-pwk",
      "@type": "lexicog:Entry",
      "lexicog:describes": {
        "@id": "https://sanskrit-lexicon.github.io/csl-standards/id/case/mw-pwg-pwk%3Aakza"
      },
      "lexicog:component": [
        {
          "@id": "https://sanskrit-lexicon.github.io/csl-standards/id/case/mw-pwg-pwk%3Aakza#sense-pwk-1"
        },
        {
          "@id": "https://sanskrit-lexicon.github.io/csl-standards/id/case/mw-pwg-pwk%3Aakza#sense-pwk-2"
        },
        {
          "@id": "https://sanskrit-lexicon.github.io/csl-standards/id/case/mw-pwg-pwk%3Aakza#sense-pwk-3"
        },
        {
          "@id": "https://sanskrit-lexicon.github.io/csl-standards/id/case/mw-pwg-pwk%3Aakza#sense-pwk-4"
        }
      ]
    },
    {
      "@id": "https://sanskrit-lexicon.github.io/csl-standards/id/case/mw-pwg-pwk%3Aakza#lexentry-gra",
      "@type": "lexicog:Entry",
      "lexicog:describes": {
        "@id": "https://sanskrit-lexicon.github.io/csl-standards/id/case/mw-pwg-pwk%3Aakza"
      },
      "lexicog:component": [
        {
          "@id": "https://sanskrit-lexicon.github.io/csl-standards/id/case/mw-pwg-pwk%3Aakza#sense-gra-1"
        }
      ]
    },
    {
      "@id": "https://sanskrit-lexicon.github.io/csl-standards/id/case/mw-pwg-pwk%3Aakza#lexentry-fri",
      "@type": "lexicog:Entry",
      "lexicog:describes": {
        "@id": "https://sanskrit-lexicon.github.io/csl-standards/id/case/mw-pwg-pwk%3Aakza"
      },
      "lexicog:component": [
        {
          "@id": "https://sanskrit-lexicon.github.io/csl-standards/id/case/mw-pwg-pwk%3Aakza#sense-fri-1"
        }
      ]
    },
    {
      "@id": "https://sanskrit-lexicon.github.io/csl-standards/id/case/mw-pwg-pwk%3Aakza#sense-mw-1",
      "@type": "ontolex:LexicalSense",
      "ontolex:isSenseOf": {
        "@id": "https://sanskrit-lexicon.github.io/csl-standards/id/case/mw-pwg-pwk%3Aakza"
      },
      "skos:definition": {
        "@value": "an axle, axis (in this sense also n., )",
        "@language": "en"
      },
      "csl:sourceDictionary": "mw"
    },
    {
      "@id": "https://sanskrit-lexicon.github.io/csl-standards/id/case/mw-pwg-pwk%3Aakza#sense-pwg-1",
      "@type": "ontolex:LexicalSense",
      "ontolex:isSenseOf": {
        "@id": "https://sanskrit-lexicon.github.io/csl-standards/id/case/mw-pwg-pwk%3Aakza"
      },
      "skos:definition": {
        "@value": "Achse am Wagen",
        "@language": "de"
      },
      "csl:sourceDictionary": "pwg"
    },
    {
      "@id": "https://sanskrit-lexicon.github.io/csl-standards/id/case/mw-pwg-pwk%3Aakza#sense-pwg-2",
      "@type": "ontolex:LexicalSense",
      "ontolex:isSenseOf": {
        "@id": "https://sanskrit-lexicon.github.io/csl-standards/id/case/mw-pwg-pwk%3Aakza"
      },
      "skos:definition": {
        "@value": "Rad",
        "@language": "de"
      },
      "csl:sourceDictionary": "pwg"
    },
    {
      "@id": "https://sanskrit-lexicon.github.io/csl-standards/id/case/mw-pwg-pwk%3Aakza#sense-pwg-3",
      "@type": "ontolex:LexicalSense",
      "ontolex:isSenseOf": {
        "@id": "https://sanskrit-lexicon.github.io/csl-standards/id/case/mw-pwg-pwk%3Aakza"
      },
      "skos:definition": {
        "@value": "Karren",
        "@language": "de"
      },
      "csl:sourceDictionary": "pwg"
    },
    {
      "@id": "https://sanskrit-lexicon.github.io/csl-standards/id/case/mw-pwg-pwk%3Aakza#sense-pwg-4",
      "@type": "ontolex:LexicalSense",
      "ontolex:isSenseOf": {
        "@id": "https://sanskrit-lexicon.github.io/csl-standards/id/case/mw-pwg-pwk%3Aakza"
      },
      "skos:definition": {
        "@value": "eine auf zwei Pfosten ruhende Platte; an die eine Wage gehängt wird(?)",
        "@language": "de"
      },
      "csl:sourceDictionary": "pwg"
    },
    {
      "@id": "https://sanskrit-lexicon.github.io/csl-standards/id/case/mw-pwg-pwk%3Aakza#sense-pwg-5",
      "@type": "ontolex:LexicalSense",
      "ontolex:isSenseOf": {
        "@id": "https://sanskrit-lexicon.github.io/csl-standards/id/case/mw-pwg-pwk%3Aakza"
      },
      "skos:definition": {
        "@value": "Auge",
        "@language": "de"
      },
      "csl:sourceDictionary": "pwg"
    },
    {
      "@id": "https://sanskrit-lexicon.github.io/csl-standards/id/case/mw-pwg-pwk%3Aakza#sense-pwg-6",
      "@type": "ontolex:LexicalSense",
      "ontolex:isSenseOf": {
        "@id": "https://sanskrit-lexicon.github.io/csl-standards/id/case/mw-pwg-pwk%3Aakza"
      },
      "skos:definition": {
        "@value": "die Gegend unterhalb der Schläfen",
        "@language": "de"
      },
      "csl:sourceDictionary": "pwg"
    },
    {
      "@id": "https://sanskrit-lexicon.github.io/csl-standards/id/case/mw-pwg-pwk%3Aakza#sense-pwk-1",
      "@type": "ontolex:LexicalSense",
      "ontolex:isSenseOf": {
        "@id": "https://sanskrit-lexicon.github.io/csl-standards/id/case/mw-pwg-pwk%3Aakza"
      },
      "skos:definition": {
        "@value": "Sinnesorgan",
        "@language": "de"
      },
      "csl:sourceDictionary": "pwk"
    },
    {
      "@id": "https://sanskrit-lexicon.github.io/csl-standards/id/case/mw-pwg-pwk%3Aakza#sense-pwk-2",
      "@type": "ontolex:LexicalSense",
      "ontolex:isSenseOf": {
        "@id": "https://sanskrit-lexicon.github.io/csl-standards/id/case/mw-pwg-pwk%3Aakza"
      },
      "skos:definition": {
        "@value": "Auge",
        "@language": "de"
      },
      "csl:sourceDictionary": "pwk"
    },
    {
      "@id": "https://sanskrit-lexicon.github.io/csl-standards/id/case/mw-pwg-pwk%3Aakza#sense-pwk-3",
      "@type": "ontolex:LexicalSense",
      "ontolex:isSenseOf": {
        "@id": "https://sanskrit-lexicon.github.io/csl-standards/id/case/mw-pwg-pwk%3Aakza"
      },
      "skos:definition": {
        "@value": "Masche",
        "@language": "de"
      },
      "csl:sourceDictionary": "pwk"
    },
    {
      "@id": "https://sanskrit-lexicon.github.io/csl-standards/id/case/mw-pwg-pwk%3Aakza#sense-pwk-4",
      "@type": "ontolex:LexicalSense",
      "ontolex:isSenseOf": {
        "@id": "https://sanskrit-lexicon.github.io/csl-standards/id/case/mw-pwg-pwk%3Aakza"
      },
      "skos:definition": {
        "@value": "Seele",
        "@language": "de"
      },
      "csl:sourceDictionary": "pwk"
    },
    {
      "@id": "https://sanskrit-lexicon.github.io/csl-standards/id/case/mw-pwg-pwk%3Aakza#sense-gra-1",
      "@type": "ontolex:LexicalSense",
      "ontolex:isSenseOf": {
        "@id": "https://sanskrit-lexicon.github.io/csl-standards/id/case/mw-pwg-pwk%3Aakza"
      },
      "skos:definition": {
        "@value": "Achse am Wagen",
        "@language": "de"
      },
      "csl:sourceDictionary": "gra"
    },
    {
      "@id": "https://sanskrit-lexicon.github.io/csl-standards/id/case/mw-pwg-pwk%3Aakza#sense-fri-1",
      "@type": "ontolex:LexicalSense",
      "ontolex:isSenseOf": {
        "@id": "https://sanskrit-lexicon.github.io/csl-standards/id/case/mw-pwg-pwk%3Aakza"
      },
      "skos:definition": [
        {
          "@value": "a die for gambling; n. pr. name of a demon",
          "@language": "en"
        },
        {
          "@value": "(игральная) кость; n. pr. имя демона",
          "@language": "ru"
        },
        {
          "@value": "kostka (ke hře); n. pr. jméno démona",
          "@language": "cs"
        }
      ],
      "csl:sourceDictionary": "fri"
    },
    {
      "@id": "https://sanskrit-lexicon.github.io/csl-standards/id/case/mw-pwg-pwk%3Aakza#record-mw",
      "@type": "csl:SourceRecord",
      "dct:source": "Monier-Williams 1899",
      "csl:dictionary": "mw",
      "csl:recordNumber": "424",
      "csl:lineNumber": 1559,
      "csl:pageColumn": "3,1",
      "rdf:value": "<L>424<pc>3,1<k1>akza<k2>a/kza<h>1<e>2\r\n<hom>1.</hom> <s>a/kza</s> ¦ <lex>m.</lex> an axle, axis (in this sense also <lex type=\"hwalt\">n.</lex>, <ls>L.</ls>)<info lex=\"m:n\"/><listinfo n=\"sup\"/>\r\n<LEND>"
    },
    {
      "@id": "https://sanskrit-lexicon.github.io/csl-standards/id/case/mw-pwg-pwk%3Aakza#record-pwg",
      "@type": "csl:SourceRecord",
      "dct:source": "Boehtlingk-Roth PWG",
      "csl:dictionary": "pwg",
      "csl:recordNumber": "167",
      "csl:lineNumber": 1359,
      "csl:pageColumn": "1-0013",
      "rdf:value": "<L>167<pc>1-0013<k1>akza<k2>a/kza<h>2\n2. {#a/kza#}¦ <lex>m.</lex>\n<ls>ŚĀNT. 2,12.</ls>\n<div n=\"1\"> 1) {%Achse am Wagen%}\n<ls>P. 5,4,74.</ls>\n<ls>H. an. 2,556</ls> ({#raTasyAvayave#}).\n[Page1-0014]\n<ls>VAIJ.</ls> beim <ab>Sch.</ab> zu <ls>ŚIŚ. 12,2.</ls> ({#akzaScakraDAraRe#}) und zu <ls n=\"ŚIŚ.\">18,7.</ls>\n({#akzaM#} [sic] {#raTANga ADAre)#}.{# akza\\M na ca\\kryo^H#}\n<ls>ṚV. 1,30,14.</ls> <ls n=\"ṚV.\">6,24,3.</ls> {#yo akze^Reva ca\\kriyA\\ SacI^Bi\\rvizva^kta\\stamBa^ pfTi\\vImu\\ta dyAm#}\n<ls n=\"ṚV.\">10,89,4.</ls> {#akzo^ vaSca\\krA sa\\mayA\\ vi vA^vfte#}\n<ls n=\"ṚV.\">1,166,9.</ls> {#sTi\\rO gAvO^ BavataM vI\\Lurakzo\\ mezA vi va^rhi\\ mA yu\\gaM vi SA^ri#}\n<ls n=\"ṚV.\">3,53,17.</ls> {#akzaBaNge#}\n<ls>M. 8,291.</ls> {#dfQaDUrakzaH#}\n<ls>P. 5,4,74</ls>, <ab>Sch.</ab>\n{#akzaDUH#}\n<ls>VOP. 6,73.</ls>\n<ls>ŚIŚ. 18,7.</ls> <ab>Vgl.</ab> {#akzAgrakIla#} und {#akzAgrakIlaka#} .\n<div n=\"1\">— 2) {%Rad%}\n<ls>AK. 3,4,224.</ls>\n<ls>MED. ṣ. 3.</ls>\n<div n=\"1\">— 3) {%Karren%}\n<ls>H. an. 2,556.</ls>\n<ls>MED. ṣ. 2.</ls>\n<div n=\"1\">— 4) {%eine auf zwei Pfosten ruhende Platte%} ({#pawwa#}), {%an die eine Wage gehängt wird(?)%}: {#akzaH pAdastamBayorupari nivizwatulADArapawwaH#}\n<ls>MIT. 146,1.</ls>\n<div n=\"1\">— 5) {%Auge%} in übertragener Bedeutung am Ende einiger Composita: {#puzkarAkzaH#}\n<ls>P. 5,4,76</ls>, <ab>Sch.</ab>\n{#gavAkzaH#} <ab>ibid.</ab> und\n<ls>VOP. 6,77.</ls> <ab>Vgl.</ab> {#akza#} <lex>n.</lex>, {#akzan#} und {#akzi#} .\n<div n=\"1\">— 6) {%die Gegend unterhalb der Schläfen%}\n<ls>YĀJÑ. 3,87.</ls> (<ls>VIJÑĀNEŚVARA</ls>: {#akzaH karRanetrayormaDye SaNKAdaDoBAgaH#}).\n<div n=\"1\">— 7) Name einer Pflanze, {%Terminalia Bellerica%},\n<ls>AK. 2,4,2,39.</ls> <ls n=\"AK.\">3,4,224.</ls>\n<ls>H. 1145.</ls>\n<ls>an. 2,556.</ls>\n<ls>MED. ṣ. 3.</ls> <is>Suśr</is>. Die Synonyme {#kali#} und {#viBIdaka (viBItaka)#} bedeuten gleichfalls {%Würfel%} ({#a/kza#}), da dazu die Nüsse der {%Terminalia Bellerica%} gebraucht wurden; <ab>vgl.</ab>\n<ls>ROTH</ls> in <ls>Z. d. d. m. G. II,123.</ls>\n<div n=\"1\">— 8) {%die Nuss der Terminalia Bellerica%}: {#yaTA vE dve vAmalake dve vA kole dvO vAkzO#}\n(<ab>Sch.</ab> = {#viBItakaPale) muzwiranuBavati#}\n<ls>CHĀND. UP. 7,3,1.</ls> {#DArABirakzamAtrABiH#}\n<ls>ARJ. 8,4.</ls>\n<F>*Diese und die vorhergehende Bedeutung, die, wie wir auch oben angedeutet haben, in der innigsten Verbindung mit {#akza#} {%Würfel%} stehen, haben wir des Accents wegen hierher gezogen.\n<ls>ŚĀNT. 2,12.</ls> heisst es nämlich, dass {#akza#}, wenn es nicht {%Würfel%} bedeute, den Ton auf der ersten Silbe habe.</F>\n<div n=\"1\">— 9) {%Elaeocarpus Ganitrus%} <is>Suśr</is>.\n<div n=\"1\">— 10) {%der Saame dieser Pflanze%}, der zu Rosenkränzen gebraucht wird ({#rudrAkze#})\n<ls>MED. ṣ. 3</ls>; <ab>vgl.</ab> {#akzamAlA#} .\n<div n=\"1\">— 11) {%der Saame einer anderen Pflanze%} ({#indrAkze#})\n<ls>MED. ṣ. 3.</ls>\n<div n=\"1\">— 12) Name eines Gewichts, ein <is>karṣa</is> =\n16 <is>māṣaka</is>\n<ls>AK. 2,9,86.</ls> <ls n=\"AK.\">3,4,224.</ls>\n<ls>H. 884.</ls>\n<ls>an. 2,556.</ls>\n<ls>MED. ṣ. 3.</ls>\n<div n=\"1\">— 13) {%Schlange%}\n<ls>MED. ṣ. 3.</ls>\n<div n=\"1\">— 14) <is>Garuḍa</is>,\n<ls>ŚABDAR.</ls> im <ls>ŚKDR.</ls>\n<div n=\"1\">— 15) {%Process%}\n<ls>AK. 3,4,224.</ls>\n<ls>H. an. 2,556.</ls>\n<ls>MED. ṣ. 2.</ls> <ab>Vgl.</ab> {#akzadarSaka, akzadfS, akzapawala, akzapAwaka#} .\n<div n=\"1\">— 16) {%Kenntniss%}\n<ls>H. an. 2,556.</ls> ({#jYAne#})\n<ls>MED. ṣ. 2.</ls> (wenn {#jYAnArTa#} <ab>st.</ab> {#jYAtArTa#} zu lesen ist, dann müsste noch {#arTa#} als besondere Bedeutung aufgeführt werden; <ab>vgl.</ab>\n8° {%affaire, transaction%} bei\n<ls>LOIS.</ls> zu <ls>AK. 3,4,224</ls>).\n<div n=\"1\">— 17) {%Seele%}\n<ls>H. an. 2,556.</ls>\n<div n=\"1\">— 18) {%ein Blindgeborner%}\n<ls>ŚABDAR.</ls> im <ls>ŚKDR.</ls>\n({#jAtAnDa#}, vielleicht ein verlesenes {#jYAnArTa#}, von dem oben <ab>u.</ab> 16. die Rede war).\n<div n=\"1\">— 19) <ab>Nom. pr.</ab> eines Mannes, <is>Rāvaṇa's</is> Sohn\n<ls>H. an. 2,556.</ls>\n<ls>R. 1,1,73.</ls>\n<ls>RAGH. 12,63.</ls> ein König, Sohn <is>Nara's</is>\n<ls>RĀJA-TAR. 1,340.</ls>\n<div n=\"1\">— 20) Zur astronomischen Bedeutung von {#akza#} ({%terrestrial latitude%},\n<ls>WILS.</ls>) <ab>vgl.</ab> folgende Citate im\n<ls>ŚKDR.</ls> : {#candrASviniGnA palaBArdDitA ca laNkAvaDiH syAdiha dakziRo 'kzaH . iti BAsvatI . praBA SaraGnA svaturIyayogAdakzaH sadA dakziRadikpradizwaH . iti jAtakArRavaH . dakziRottarareKAyAM sA tatra vizuvatpraBA SaNkucCAyAhate trijye vizuvatkarRaBAjite . lambAkzajye tayoScApe lambAkzO dakziRO sadA . iti sUryasidDAntaH .#}\n<LEND>"
    },
    {
      "@id": "https://sanskrit-lexicon.github.io/csl-standards/id/case/mw-pwg-pwk%3Aakza#record-pwk",
      "@type": "csl:SourceRecord",
      "dct:source": "Boehtlingk PWK",
      "csl:dictionary": "pwk",
      "csl:recordNumber": "252",
      "csl:lineNumber": 936,
      "csl:pageColumn": "1-004-a",
      "rdf:value": "<L>252<pc>1-004-a<k1>akza<k2>akza<h>3\n<hom>3.</hom> {#akza#}¦\n<div n=\"1\">— 1〉 <lex>m.</lex> <lex>n.</lex> {%Sinnesorgan%}.\n<div n=\"1\">— 2〉 am Ende eines <ab>adj. Comp.</ab> (<lex>f.</lex> {#I#}) = {#akzi#}\n<div n=\"2\">— a〉 {%Auge%} <ls n=\"Chr.\">163,2</ls>. <ls n=\"Chr.\">174,5</ls>. <ls n=\"Chr.\">175,25</ls>. <ls n=\"Chr.\">184,1</ls>. <ls n=\"Chr.\">186,6</ls>.\n<div n=\"2\">— b〉 {%Masche%}.\n<div n=\"1\">— 3〉 <lex>m.</lex> {%Seele%} <ls>Ind. St. 14,382</ls>.\n<LEND>"
    },
    {
      "@id": "https://sanskrit-lexicon.github.io/csl-standards/id/case/mw-pwg-pwk%3Aakza#record-gra",
      "@type": "csl:SourceRecord",
      "dct:source": "Grassmann Wörterbuch zum Rig-Veda",
      "csl:dictionary": "gra",
      "csl:recordNumber": "44",
      "csl:lineNumber": 227,
      "csl:pageColumn": "0006",
      "rdf:value": "<L>44<pc>0006<k1>akza<k2>a/kza\r\n{@ákṣa,@}¦ <ab>m.</ab>, {%Achse am Wagen%}. Die genaue Uebereinstimmung in der Form mit akṣa, Auge (<ab n=\"siehe\">s.</ab> das folgende und <ab>vgl.</ab> ákṣi, Auge mit <lang>lat.</lang> axi-s) lässt noch immer die von <ls>Benfey (S. V. glo.)</ls> angegebene Erklärung, wonach die durch das Rad gesteckte Achse als Auge des Rades aufgefasst wurde, als die wahrscheinlichste erscheinen. <ab>Vgl.</ab> die Genetiven ráthasya, cakríos und die Zusammensetzung sam-akṣá.\r\n<div n=\"TS\">-a [<ab>V.</ab>] {287,19} (vīḍo vīḍita).\r\n<div n=\"TS\">-as {164,13}; {166,9}; {287,17}; {465,3}; {625,29}; {911,12} (ā́hatas).\r\n<div n=\"TS\">-am {30,14}. _{30,15}; {549,4}.\r\n<div n=\"TS\">-ena {915,4} (neben cakríyā).\r\n<div n=\"TS\">-e [<ab>L.</ab>] {666,27} (araṭvé).\r\n<LEND>"
    },
    {
      "@id": "https://sanskrit-lexicon.github.io/csl-standards/id/case/mw-pwg-pwk%3Aakza#record-fri",
      "@type": "csl:SourceRecord",
      "dct:source": "Frish Sanskrit Reader (Cologne 2015)",
      "csl:dictionary": "fri",
      "csl:recordNumber": "23",
      "csl:lineNumber": 118,
      "csl:pageColumn": "011",
      "rdf:value": "<L>23<pc>011<k1>akza<k2>akza\nI akṣa m.\n<div n=\"1\"/>1 <lang n=\"czech\">kostka (ke hře); n. pr. jméno démona</lang>\n<div n=\"1\"/>2 <lang n=\"russian\">(игральная) кость; n. pr. имя демона</lang>\n<div n=\"1\"/>3 <lang n=\"english\">a die for gambling; n. pr. name of a demon</lang>\n<LEND>"
    },
    {
      "@id": "https://sanskrit-lexicon.github.io/csl-standards/id/case/mw-pwg-pwk%3Aakza#record-ben",
      "@type": "csl:SourceRecord",
      "dct:source": "Benfey Sanskrit-English 1866",
      "csl:dictionary": "ben",
      "csl:recordNumber": "26",
      "csl:lineNumber": 147,
      "csl:pageColumn": "0002-b",
      "rdf:value": "<L>26<pc>0002-b<k1>akza<k2>akza\r\n1. {#akza#}¦ {%akṣa,%} probably from a lost\r\n<ab>vb.</ab> {%akṣ,%} corresponding to <lang n=\"greek\">ὀσσ</lang> in <lang n=\"greek\">ὄσσομαι</lang>\r\n{@I.@} <ab>n.</ab> {@1.@} The eye; particularly\r\nas latter part of <ab>comp.</ab> <ab>adj.</ab>, <ab>f.</ab> {%kṣī.%} {@2.@}\r\nAn organ of sense, <ls>Pañc.</ls> ii, <ab>d.</ab> 164.\r\n{@II.@} <ab>m.</ab> {@1.@} A die, <ls>Man.</ls> 4, 74. {@2.@} The\r\nname of a plant, Terminalia Bellerica,\r\nof which the nuts are used as dice, and\r\nthe seed for making rosaries. {@ -- <ab>Comp.</ab>@}\r\n{%Kamala-patra-,%} <ab>adj.</ab>, <ab>f.</ab> {%kṣī,%} <ab>adj.</ab> hav-\r\ning eyes like lotus-leaves. {%Kūṭa-,%} <ab>m.</ab> a\r\nfalse die. {%Jāla-,%} <ab>m.</ab> a lattice window.\r\n{%Tāmra-,%} <ab>adj.</ab> red-eyed. {%Tāraka-,%} 1. <ab>adj.</ab>\r\nhaving stars for eyes. 2. <ab>m.</ab> a proper\r\nname. {%Tryakṣa,%} <ab>i. e.</ab> {%tri-,%} {@I.@} <ab>adj.</ab> having\r\nthree eyes. {@II.@} <ab>m.</ab> a name of Rudra-\r\nŚiva, and of a demon. {%Daśākṣa,%} <ab>i. e.</ab>\r\n{%daśan-,%} <ab>m.</ab> the name of a spell or\r\ncharm {%Padma-,%} <ab>adj.</ab> lotus-eyed.\r\n{%Puṇḍarīka-,%} <ab>m.</ab> a name of Viṣṇu.\r\n{%Puṣkara-,%} <ab>adj.</ab> lotus-eyed. {%Manda-,%}\r\n<ab>n.</ab> modesty. {%Lohita-,%} <ab>adj.</ab> red-eyed.\r\n{%Sahasra-,%} {@I.@} <ab>adj.</ab> thousand-eyed. {@II.@} <ab>m.</ab>\r\na name of Indra. {%Su-,%} <ab>adj.</ab> 1. hand-\r\nsome-eyed. 2. acute. -- <ab>Cf.</ab> <lang n=\"greek\">ὄσσομαι, ὄκκος</lang>;\r\n<ab>Lat.</ab> oculus; and see {%akṣi.%}\r\n<LEND>"
    },
    {
      "@id": "https://sanskrit-lexicon.github.io/csl-standards/id/case/mw-pwg-pwk%3Aakza#attestation-1",
      "@type": "frac:Attestation",
      "frac:attests": {
        "@id": "https://sanskrit-lexicon.github.io/csl-standards/id/case/mw-pwg-pwk%3Aakza#sense-mw-1"
      },
      "frac:evidence": "L.",
      "prov:wasDerivedFrom": {
        "@id": "https://sanskrit-lexicon.github.io/csl-standards/id/case/mw-pwg-pwk%3Aakza#record-mw"
      },
      "csl:sourceDictionary": "mw",
      "csl:evidenceType": "generic-lexicographer-hedge",
      "csl:evidenceClass": "hedge"
    },
    {
      "@id": "https://sanskrit-lexicon.github.io/csl-standards/id/case/mw-pwg-pwk%3Aakza#attestation-2",
      "@type": "frac:Attestation",
      "frac:attests": {
        "@id": "https://sanskrit-lexicon.github.io/csl-standards/id/case/mw-pwg-pwk%3Aakza#sense-pwg-1"
      },
      "frac:evidence": "P. 5,4,74.",
      "prov:wasDerivedFrom": {
        "@id": "https://sanskrit-lexicon.github.io/csl-standards/id/case/mw-pwg-pwk%3Aakza#record-pwg"
      },
      "csl:sourceDictionary": "pwg",
      "csl:evidenceType": "named-source-citation",
      "csl:evidenceClass": "textual",
      "csl:citedWork": "P.",
      "csl:citedRange": "5,4,74"
    },
    {
      "@id": "https://sanskrit-lexicon.github.io/csl-standards/id/case/mw-pwg-pwk%3Aakza#attestation-3",
      "@type": "frac:Attestation",
      "frac:attests": {
        "@id": "https://sanskrit-lexicon.github.io/csl-standards/id/case/mw-pwg-pwk%3Aakza#sense-pwg-1"
      },
      "frac:evidence": "H. an. 2,556",
      "prov:wasDerivedFrom": {
        "@id": "https://sanskrit-lexicon.github.io/csl-standards/id/case/mw-pwg-pwk%3Aakza#record-pwg"
      },
      "csl:sourceDictionary": "pwg",
      "csl:evidenceType": "named-source-citation",
      "csl:evidenceClass": "kosha",
      "csl:citedWork": "H. an.",
      "csl:citedRange": "2,556"
    },
    {
      "@id": "https://sanskrit-lexicon.github.io/csl-standards/id/case/mw-pwg-pwk%3Aakza#attestation-4",
      "@type": "frac:Attestation",
      "frac:attests": {
        "@id": "https://sanskrit-lexicon.github.io/csl-standards/id/case/mw-pwg-pwk%3Aakza#sense-pwg-1"
      },
      "frac:evidence": "VAIJ.",
      "prov:wasDerivedFrom": {
        "@id": "https://sanskrit-lexicon.github.io/csl-standards/id/case/mw-pwg-pwk%3Aakza#record-pwg"
      },
      "csl:sourceDictionary": "pwg",
      "csl:evidenceType": "named-source-citation",
      "csl:evidenceClass": "textual"
    },
    {
      "@id": "https://sanskrit-lexicon.github.io/csl-standards/id/case/mw-pwg-pwk%3Aakza#attestation-5",
      "@type": "frac:Attestation",
      "frac:attests": {
        "@id": "https://sanskrit-lexicon.github.io/csl-standards/id/case/mw-pwg-pwk%3Aakza#sense-pwg-1"
      },
      "frac:evidence": "ŚIŚ. 12,2.",
      "prov:wasDerivedFrom": {
        "@id": "https://sanskrit-lexicon.github.io/csl-standards/id/case/mw-pwg-pwk%3Aakza#record-pwg"
      },
      "csl:sourceDictionary": "pwg",
      "csl:evidenceType": "named-source-citation",
      "csl:evidenceClass": "textual",
      "csl:citedWork": "ŚIŚ.",
      "csl:citedRange": "12,2"
    },
    {
      "@id": "https://sanskrit-lexicon.github.io/csl-standards/id/case/mw-pwg-pwk%3Aakza#attestation-6",
      "@type": "frac:Attestation",
      "frac:attests": {
        "@id": "https://sanskrit-lexicon.github.io/csl-standards/id/case/mw-pwg-pwk%3Aakza#sense-pwg-1"
      },
      "frac:evidence": "18,7.",
      "prov:wasDerivedFrom": {
        "@id": "https://sanskrit-lexicon.github.io/csl-standards/id/case/mw-pwg-pwk%3Aakza#record-pwg"
      },
      "csl:sourceDictionary": "pwg",
      "csl:evidenceType": "named-source-citation",
      "csl:evidenceClass": "textual",
      "csl:inheritedSiglum": "ŚIŚ."
    },
    {
      "@id": "https://sanskrit-lexicon.github.io/csl-standards/id/case/mw-pwg-pwk%3Aakza#attestation-7",
      "@type": "frac:Attestation",
      "frac:attests": {
        "@id": "https://sanskrit-lexicon.github.io/csl-standards/id/case/mw-pwg-pwk%3Aakza#sense-pwg-1"
      },
      "frac:evidence": "ṚV. 1,30,14.",
      "prov:wasDerivedFrom": {
        "@id": "https://sanskrit-lexicon.github.io/csl-standards/id/case/mw-pwg-pwk%3Aakza#record-pwg"
      },
      "csl:sourceDictionary": "pwg",
      "csl:evidenceType": "named-source-citation",
      "csl:evidenceClass": "textual",
      "csl:citedWork": "ṚV.",
      "csl:citedRange": "1,30,14"
    },
    {
      "@id": "https://sanskrit-lexicon.github.io/csl-standards/id/case/mw-pwg-pwk%3Aakza#attestation-8",
      "@type": "frac:Attestation",
      "frac:attests": {
        "@id": "https://sanskrit-lexicon.github.io/csl-standards/id/case/mw-pwg-pwk%3Aakza#sense-pwg-1"
      },
      "frac:evidence": "6,24,3.",
      "prov:wasDerivedFrom": {
        "@id": "https://sanskrit-lexicon.github.io/csl-standards/id/case/mw-pwg-pwk%3Aakza#record-pwg"
      },
      "csl:sourceDictionary": "pwg",
      "csl:evidenceType": "named-source-citation",
      "csl:evidenceClass": "textual",
      "csl:inheritedSiglum": "ṚV."
    },
    {
      "@id": "https://sanskrit-lexicon.github.io/csl-standards/id/case/mw-pwg-pwk%3Aakza#attestation-9",
      "@type": "frac:Attestation",
      "frac:attests": {
        "@id": "https://sanskrit-lexicon.github.io/csl-standards/id/case/mw-pwg-pwk%3Aakza#sense-pwg-1"
      },
      "frac:evidence": "10,89,4.",
      "prov:wasDerivedFrom": {
        "@id": "https://sanskrit-lexicon.github.io/csl-standards/id/case/mw-pwg-pwk%3Aakza#record-pwg"
      },
      "csl:sourceDictionary": "pwg",
      "csl:evidenceType": "named-source-citation",
      "csl:evidenceClass": "textual",
      "csl:inheritedSiglum": "ṚV."
    },
    {
      "@id": "https://sanskrit-lexicon.github.io/csl-standards/id/case/mw-pwg-pwk%3Aakza#attestation-10",
      "@type": "frac:Attestation",
      "frac:attests": {
        "@id": "https://sanskrit-lexicon.github.io/csl-standards/id/case/mw-pwg-pwk%3Aakza#sense-pwg-1"
      },
      "frac:evidence": "1,166,9.",
      "prov:wasDerivedFrom": {
        "@id": "https://sanskrit-lexicon.github.io/csl-standards/id/case/mw-pwg-pwk%3Aakza#record-pwg"
      },
      "csl:sourceDictionary": "pwg",
      "csl:evidenceType": "named-source-citation",
      "csl:evidenceClass": "textual",
      "csl:inheritedSiglum": "ṚV."
    },
    {
      "@id": "https://sanskrit-lexicon.github.io/csl-standards/id/case/mw-pwg-pwk%3Aakza#attestation-11",
      "@type": "frac:Attestation",
      "frac:attests": {
        "@id": "https://sanskrit-lexicon.github.io/csl-standards/id/case/mw-pwg-pwk%3Aakza#sense-pwg-1"
      },
      "frac:evidence": "3,53,17.",
      "prov:wasDerivedFrom": {
        "@id": "https://sanskrit-lexicon.github.io/csl-standards/id/case/mw-pwg-pwk%3Aakza#record-pwg"
      },
      "csl:sourceDictionary": "pwg",
      "csl:evidenceType": "named-source-citation",
      "csl:evidenceClass": "textual",
      "csl:inheritedSiglum": "ṚV."
    },
    {
      "@id": "https://sanskrit-lexicon.github.io/csl-standards/id/case/mw-pwg-pwk%3Aakza#attestation-12",
      "@type": "frac:Attestation",
      "frac:attests": {
        "@id": "https://sanskrit-lexicon.github.io/csl-standards/id/case/mw-pwg-pwk%3Aakza#sense-pwg-1"
      },
      "frac:evidence": "M. 8,291.",
      "prov:wasDerivedFrom": {
        "@id": "https://sanskrit-lexicon.github.io/csl-standards/id/case/mw-pwg-pwk%3Aakza#record-pwg"
      },
      "csl:sourceDictionary": "pwg",
      "csl:evidenceType": "named-source-citation",
      "csl:evidenceClass": "textual",
      "csl:citedWork": "M.",
      "csl:citedRange": "8,291"
    },
    {
      "@id": "https://sanskrit-lexicon.github.io/csl-standards/id/case/mw-pwg-pwk%3Aakza#attestation-13",
      "@type": "frac:Attestation",
      "frac:attests": {
        "@id": "https://sanskrit-lexicon.github.io/csl-standards/id/case/mw-pwg-pwk%3Aakza#sense-pwg-1"
      },
      "frac:evidence": "P. 5,4,74",
      "prov:wasDerivedFrom": {
        "@id": "https://sanskrit-lexicon.github.io/csl-standards/id/case/mw-pwg-pwk%3Aakza#record-pwg"
      },
      "csl:sourceDictionary": "pwg",
      "csl:evidenceType": "named-source-citation",
      "csl:evidenceClass": "textual",
      "csl:citedWork": "P.",
      "csl:citedRange": "5,4,74"
    },
    {
      "@id": "https://sanskrit-lexicon.github.io/csl-standards/id/case/mw-pwg-pwk%3Aakza#attestation-14",
      "@type": "frac:Attestation",
      "frac:attests": {
        "@id": "https://sanskrit-lexicon.github.io/csl-standards/id/case/mw-pwg-pwk%3Aakza#sense-pwg-1"
      },
      "frac:evidence": "VOP. 6,73.",
      "prov:wasDerivedFrom": {
        "@id": "https://sanskrit-lexicon.github.io/csl-standards/id/case/mw-pwg-pwk%3Aakza#record-pwg"
      },
      "csl:sourceDictionary": "pwg",
      "csl:evidenceType": "named-source-citation",
      "csl:evidenceClass": "textual",
      "csl:citedWork": "VOP.",
      "csl:citedRange": "6,73"
    },
    {
      "@id": "https://sanskrit-lexicon.github.io/csl-standards/id/case/mw-pwg-pwk%3Aakza#attestation-15",
      "@type": "frac:Attestation",
      "frac:attests": {
        "@id": "https://sanskrit-lexicon.github.io/csl-standards/id/case/mw-pwg-pwk%3Aakza#sense-pwg-1"
      },
      "frac:evidence": "ŚIŚ. 18,7.",
      "prov:wasDerivedFrom": {
        "@id": "https://sanskrit-lexicon.github.io/csl-standards/id/case/mw-pwg-pwk%3Aakza#record-pwg"
      },
      "csl:sourceDictionary": "pwg",
      "csl:evidenceType": "named-source-citation",
      "csl:evidenceClass": "textual",
      "csl:citedWork": "ŚIŚ.",
      "csl:citedRange": "18,7"
    },
    {
      "@id": "https://sanskrit-lexicon.github.io/csl-standards/id/case/mw-pwg-pwk%3Aakza#attestation-16",
      "@type": "frac:Attestation",
      "frac:attests": {
        "@id": "https://sanskrit-lexicon.github.io/csl-standards/id/case/mw-pwg-pwk%3Aakza#sense-pwg-2"
      },
      "frac:evidence": "AK. 3,4,224.",
      "prov:wasDerivedFrom": {
        "@id": "https://sanskrit-lexicon.github.io/csl-standards/id/case/mw-pwg-pwk%3Aakza#record-pwg"
      },
      "csl:sourceDictionary": "pwg",
      "csl:evidenceType": "named-source-citation",
      "csl:evidenceClass": "kosha",
      "csl:citedWork": "AK.",
      "csl:citedRange": "3,4,224"
    },
    {
      "@id": "https://sanskrit-lexicon.github.io/csl-standards/id/case/mw-pwg-pwk%3Aakza#attestation-17",
      "@type": "frac:Attestation",
      "frac:attests": {
        "@id": "https://sanskrit-lexicon.github.io/csl-standards/id/case/mw-pwg-pwk%3Aakza#sense-pwg-2"
      },
      "frac:evidence": "MED. ṣ. 3.",
      "prov:wasDerivedFrom": {
        "@id": "https://sanskrit-lexicon.github.io/csl-standards/id/case/mw-pwg-pwk%3Aakza#record-pwg"
      },
      "csl:sourceDictionary": "pwg",
      "csl:evidenceType": "named-source-citation",
      "csl:evidenceClass": "textual"
    },
    {
      "@id": "https://sanskrit-lexicon.github.io/csl-standards/id/case/mw-pwg-pwk%3Aakza#attestation-18",
      "@type": "frac:Attestation",
      "frac:attests": {
        "@id": "https://sanskrit-lexicon.github.io/csl-standards/id/case/mw-pwg-pwk%3Aakza#sense-pwg-3"
      },
      "frac:evidence": "H. an. 2,556.",
      "prov:wasDerivedFrom": {
        "@id": "https://sanskrit-lexicon.github.io/csl-standards/id/case/mw-pwg-pwk%3Aakza#record-pwg"
      },
      "csl:sourceDictionary": "pwg",
      "csl:evidenceType": "named-source-citation",
      "csl:evidenceClass": "kosha",
      "csl:citedWork": "H. an.",
      "csl:citedRange": "2,556"
    },
    {
      "@id": "https://sanskrit-lexicon.github.io/csl-standards/id/case/mw-pwg-pwk%3Aakza#attestation-19",
      "@type": "frac:Attestation",
      "frac:attests": {
        "@id": "https://sanskrit-lexicon.github.io/csl-standards/id/case/mw-pwg-pwk%3Aakza#sense-pwg-3"
      },
      "frac:evidence": "MED. ṣ. 2.",
      "prov:wasDerivedFrom": {
        "@id": "https://sanskrit-lexicon.github.io/csl-standards/id/case/mw-pwg-pwk%3Aakza#record-pwg"
      },
      "csl:sourceDictionary": "pwg",
      "csl:evidenceType": "named-source-citation",
      "csl:evidenceClass": "textual"
    },
    {
      "@id": "https://sanskrit-lexicon.github.io/csl-standards/id/case/mw-pwg-pwk%3Aakza#attestation-20",
      "@type": "frac:Attestation",
      "frac:attests": {
        "@id": "https://sanskrit-lexicon.github.io/csl-standards/id/case/mw-pwg-pwk%3Aakza#sense-pwg-4"
      },
      "frac:evidence": "MIT. 146,1.",
      "prov:wasDerivedFrom": {
        "@id": "https://sanskrit-lexicon.github.io/csl-standards/id/case/mw-pwg-pwk%3Aakza#record-pwg"
      },
      "csl:sourceDictionary": "pwg",
      "csl:evidenceType": "named-source-citation",
      "csl:evidenceClass": "textual",
      "csl:citedWork": "MIT.",
      "csl:citedRange": "146,1"
    },
    {
      "@id": "https://sanskrit-lexicon.github.io/csl-standards/id/case/mw-pwg-pwk%3Aakza#attestation-21",
      "@type": "frac:Attestation",
      "frac:attests": {
        "@id": "https://sanskrit-lexicon.github.io/csl-standards/id/case/mw-pwg-pwk%3Aakza#sense-pwg-5"
      },
      "frac:evidence": "P. 5,4,76",
      "prov:wasDerivedFrom": {
        "@id": "https://sanskrit-lexicon.github.io/csl-standards/id/case/mw-pwg-pwk%3Aakza#record-pwg"
      },
      "csl:sourceDictionary": "pwg",
      "csl:evidenceType": "named-source-citation",
      "csl:evidenceClass": "textual",
      "csl:citedWork": "P.",
      "csl:citedRange": "5,4,76"
    },
    {
      "@id": "https://sanskrit-lexicon.github.io/csl-standards/id/case/mw-pwg-pwk%3Aakza#attestation-22",
      "@type": "frac:Attestation",
      "frac:attests": {
        "@id": "https://sanskrit-lexicon.github.io/csl-standards/id/case/mw-pwg-pwk%3Aakza#sense-pwg-5"
      },
      "frac:evidence": "VOP. 6,77.",
      "prov:wasDerivedFrom": {
        "@id": "https://sanskrit-lexicon.github.io/csl-standards/id/case/mw-pwg-pwk%3Aakza#record-pwg"
      },
      "csl:sourceDictionary": "pwg",
      "csl:evidenceType": "named-source-citation",
      "csl:evidenceClass": "textual",
      "csl:citedWork": "VOP.",
      "csl:citedRange": "6,77"
    },
    {
      "@id": "https://sanskrit-lexicon.github.io/csl-standards/id/case/mw-pwg-pwk%3Aakza#attestation-23",
      "@type": "frac:Attestation",
      "frac:attests": {
        "@id": "https://sanskrit-lexicon.github.io/csl-standards/id/case/mw-pwg-pwk%3Aakza#sense-pwg-6"
      },
      "frac:evidence": "YĀJÑ. 3,87.",
      "prov:wasDerivedFrom": {
        "@id": "https://sanskrit-lexicon.github.io/csl-standards/id/case/mw-pwg-pwk%3Aakza#record-pwg"
      },
      "csl:sourceDictionary": "pwg",
      "csl:evidenceType": "named-source-citation",
      "csl:evidenceClass": "textual",
      "csl:citedWork": "YĀJÑ.",
      "csl:citedRange": "3,87"
    },
    {
      "@id": "https://sanskrit-lexicon.github.io/csl-standards/id/case/mw-pwg-pwk%3Aakza#attestation-24",
      "@type": "frac:Attestation",
      "frac:attests": {
        "@id": "https://sanskrit-lexicon.github.io/csl-standards/id/case/mw-pwg-pwk%3Aakza#sense-pwg-6"
      },
      "frac:evidence": "VIJÑĀNEŚVARA",
      "prov:wasDerivedFrom": {
        "@id": "https://sanskrit-lexicon.github.io/csl-standards/id/case/mw-pwg-pwk%3Aakza#record-pwg"
      },
      "csl:sourceDictionary": "pwg",
      "csl:evidenceType": "named-source-citation",
      "csl:evidenceClass": "textual"
    },
    {
      "@id": "https://sanskrit-lexicon.github.io/csl-standards/id/case/mw-pwg-pwk%3Aakza#attestation-25",
      "@type": "frac:Attestation",
      "frac:attests": {
        "@id": "https://sanskrit-lexicon.github.io/csl-standards/id/case/mw-pwg-pwk%3Aakza#sense-pwk-2"
      },
      "frac:evidence": "163,2",
      "prov:wasDerivedFrom": {
        "@id": "https://sanskrit-lexicon.github.io/csl-standards/id/case/mw-pwg-pwk%3Aakza#record-pwk"
      },
      "csl:sourceDictionary": "pwk",
      "csl:evidenceType": "named-source-citation",
      "csl:evidenceClass": "textual",
      "csl:inheritedSiglum": "Chr."
    },
    {
      "@id": "https://sanskrit-lexicon.github.io/csl-standards/id/case/mw-pwg-pwk%3Aakza#attestation-26",
      "@type": "frac:Attestation",
      "frac:attests": {
        "@id": "https://sanskrit-lexicon.github.io/csl-standards/id/case/mw-pwg-pwk%3Aakza#sense-pwk-2"
      },
      "frac:evidence": "174,5",
      "prov:wasDerivedFrom": {
        "@id": "https://sanskrit-lexicon.github.io/csl-standards/id/case/mw-pwg-pwk%3Aakza#record-pwk"
      },
      "csl:sourceDictionary": "pwk",
      "csl:evidenceType": "named-source-citation",
      "csl:evidenceClass": "textual",
      "csl:inheritedSiglum": "Chr."
    },
    {
      "@id": "https://sanskrit-lexicon.github.io/csl-standards/id/case/mw-pwg-pwk%3Aakza#attestation-27",
      "@type": "frac:Attestation",
      "frac:attests": {
        "@id": "https://sanskrit-lexicon.github.io/csl-standards/id/case/mw-pwg-pwk%3Aakza#sense-pwk-2"
      },
      "frac:evidence": "175,25",
      "prov:wasDerivedFrom": {
        "@id": "https://sanskrit-lexicon.github.io/csl-standards/id/case/mw-pwg-pwk%3Aakza#record-pwk"
      },
      "csl:sourceDictionary": "pwk",
      "csl:evidenceType": "named-source-citation",
      "csl:evidenceClass": "textual",
      "csl:inheritedSiglum": "Chr."
    },
    {
      "@id": "https://sanskrit-lexicon.github.io/csl-standards/id/case/mw-pwg-pwk%3Aakza#attestation-28",
      "@type": "frac:Attestation",
      "frac:attests": {
        "@id": "https://sanskrit-lexicon.github.io/csl-standards/id/case/mw-pwg-pwk%3Aakza#sense-pwk-2"
      },
      "frac:evidence": "184,1",
      "prov:wasDerivedFrom": {
        "@id": "https://sanskrit-lexicon.github.io/csl-standards/id/case/mw-pwg-pwk%3Aakza#record-pwk"
      },
      "csl:sourceDictionary": "pwk",
      "csl:evidenceType": "named-source-citation",
      "csl:evidenceClass": "textual",
      "csl:inheritedSiglum": "Chr."
    },
    {
      "@id": "https://sanskrit-lexicon.github.io/csl-standards/id/case/mw-pwg-pwk%3Aakza#attestation-29",
      "@type": "frac:Attestation",
      "frac:attests": {
        "@id": "https://sanskrit-lexicon.github.io/csl-standards/id/case/mw-pwg-pwk%3Aakza#sense-pwk-2"
      },
      "frac:evidence": "186,6",
      "prov:wasDerivedFrom": {
        "@id": "https://sanskrit-lexicon.github.io/csl-standards/id/case/mw-pwg-pwk%3Aakza#record-pwk"
      },
      "csl:sourceDictionary": "pwk",
      "csl:evidenceType": "named-source-citation",
      "csl:evidenceClass": "textual",
      "csl:inheritedSiglum": "Chr."
    },
    {
      "@id": "https://sanskrit-lexicon.github.io/csl-standards/id/case/mw-pwg-pwk%3Aakza#attestation-30",
      "@type": "frac:Attestation",
      "frac:attests": {
        "@id": "https://sanskrit-lexicon.github.io/csl-standards/id/case/mw-pwg-pwk%3Aakza#sense-pwk-4"
      },
      "frac:evidence": "Ind. St. 14,382",
      "prov:wasDerivedFrom": {
        "@id": "https://sanskrit-lexicon.github.io/csl-standards/id/case/mw-pwg-pwk%3Aakza#record-pwk"
      },
      "csl:sourceDictionary": "pwk",
      "csl:evidenceType": "named-source-citation",
      "csl:evidenceClass": "textual",
      "csl:citedWork": "Ind. St.",
      "csl:citedRange": "14,382"
    },
    {
      "@id": "https://sanskrit-lexicon.github.io/csl-standards/id/case/mw-pwg-pwk%3Aakza#attestation-31",
      "@type": "frac:Attestation",
      "frac:attests": {
        "@id": "https://sanskrit-lexicon.github.io/csl-standards/id/case/mw-pwg-pwk%3Aakza#sense-gra-1"
      },
      "frac:evidence": "Benfey (S. V. glo.)",
      "prov:wasDerivedFrom": {
        "@id": "https://sanskrit-lexicon.github.io/csl-standards/id/case/mw-pwg-pwk%3Aakza#record-gra"
      },
      "csl:sourceDictionary": "gra",
      "csl:evidenceType": "named-source-citation",
      "csl:evidenceClass": "textual"
    },
    {
      "@id": "https://sanskrit-lexicon.github.io/csl-standards/id/case/mw-pwg-pwk%3Aakza#attestation-32",
      "@type": "frac:Attestation",
      "frac:attests": {
        "@id": "https://sanskrit-lexicon.github.io/csl-standards/id/case/mw-pwg-pwk%3Aakza"
      },
      "frac:evidence": "ŚĀNT. 2,12.",
      "prov:wasDerivedFrom": {
        "@id": "https://sanskrit-lexicon.github.io/csl-standards/id/case/mw-pwg-pwk%3Aakza#record-pwg"
      },
      "csl:sourceDictionary": "pwg",
      "csl:evidenceType": "named-source-citation",
      "csl:evidenceClass": "textual",
      "csl:citedWork": "ŚĀNT.",
      "csl:citedRange": "2,12"
    },
    {
      "@id": "https://sanskrit-lexicon.github.io/csl-standards/id/case/mw-pwg-pwk%3Aakza#attestation-33",
      "@type": "frac:Attestation",
      "frac:attests": {
        "@id": "https://sanskrit-lexicon.github.io/csl-standards/id/case/mw-pwg-pwk%3Aakza"
      },
      "frac:evidence": "Pañc.",
      "prov:wasDerivedFrom": {
        "@id": "https://sanskrit-lexicon.github.io/csl-standards/id/case/mw-pwg-pwk%3Aakza#record-ben"
      },
      "csl:sourceDictionary": "ben",
      "csl:evidenceType": "named-source-citation",
      "csl:evidenceClass": "textual"
    },
    {
      "@id": "https://sanskrit-lexicon.github.io/csl-standards/id/case/mw-pwg-pwk%3Aakza#attestation-34",
      "@type": "frac:Attestation",
      "frac:attests": {
        "@id": "https://sanskrit-lexicon.github.io/csl-standards/id/case/mw-pwg-pwk%3Aakza"
      },
      "frac:evidence": "Man.",
      "prov:wasDerivedFrom": {
        "@id": "https://sanskrit-lexicon.github.io/csl-standards/id/case/mw-pwg-pwk%3Aakza#record-ben"
      },
      "csl:sourceDictionary": "ben",
      "csl:evidenceType": "named-source-citation",
      "csl:evidenceClass": "textual"
    },
    {
      "@id": "https://sanskrit-lexicon.github.io/csl-standards/id/case/mw-pwg-pwk%3Aakza#lineage-pwk",
      "@type": "csl:LineageRelation",
      "csl:relatesEntry": {
        "@id": "https://sanskrit-lexicon.github.io/csl-standards/id/case/mw-pwg-pwk%3Aakza"
      },
      "csl:lineageFrom": "pwg",
      "csl:lineageTo": "pwk",
      "csl:transition": "abridgement",
      "csl:sourceCitationCount": 24,
      "csl:retainedCitationCount": 6,
      "csl:droppedCitationCount": 18,
      "csl:modelingNote": "PWK abridges PWG's named apparatus; dropped citations are upstream editorial loss, not a model gap."
    },
    {
      "@id": "https://sanskrit-lexicon.github.io/csl-standards/id/case/mw-pwg-pwk%3Aakza#lineage-mw",
      "@type": "csl:LineageRelation",
      "csl:relatesEntry": {
        "@id": "https://sanskrit-lexicon.github.io/csl-standards/id/case/mw-pwg-pwk%3Aakza"
      },
      "csl:lineageFrom": "pwg",
      "csl:lineageTo": "mw",
      "csl:transition": "recomposition",
      "csl:sourceCitationCount": 24,
      "csl:retainedCitationCount": 1,
      "csl:droppedCitationCount": 23,
      "csl:modelingNote": "MW recomposes the Petersburg dictionaries in English, collapsing named sources to the L. hedge or dropping them."
    }
  ]
}
