<entry xml:id="mw-pwg-pwk-aMSa">
  <form type="continuation">
    <orth notation="SLP1">aMSa</orth>
  </form>
  <xr type="adjacency-continuation-parent" target="1A"/>
  <note type="source" target="mw">&lt;L&gt;15&lt;pc&gt;1,1&lt;k1&gt;aMSa&lt;k2&gt;a/MSa&lt;e&gt;1A ¦ a lot (&lt;ab&gt;cf.&lt;/ab&gt; &lt;hom&gt;2.&lt;/hom&gt; &lt;s&gt;prA&lt;srs/&gt;s&lt;/s&gt;)&lt;info lex=&quot;inh&quot;/&gt; &lt;LEND&gt;</note>
  <note type="source" target="pwg">&lt;L&gt;7&lt;pc&gt;1-0003&lt;k1&gt;aMSa&lt;k2&gt;a/MSa&lt;h&gt;1 1. {#a/MSa#}¦ (s. &lt;is&gt;gaṇa&lt;/is&gt; {#vfzAdi#}) &lt;lex&gt;m.&lt;/lex&gt; &lt;ls&gt;SIDDH. K. 249,b, ult.&lt;/ls&gt; &lt;div n=&quot;1&quot;&gt; 1) {%Theil%} &lt;ls&gt;AK. 2,9,90.&lt;/ls&gt; &lt;ls&gt;H. 1434.&lt;/ls&gt; &lt;div n=&quot;2&quot;&gt;— a) {%Theil, Abschnitt%} &lt;ls&gt;H. an. 2,542.&lt;/ls&gt; ({#ekadeSe vastunaH#}): {#zoqaSoM &apos;SaH#} ({#candrasya#}) {#kalA#} {%der 16te Theil (des Mondes) heisst%} &lt;is&gt;kalā&lt;/is&gt; &lt;ls&gt;H. 106.&lt;/ls&gt; {#tUryaMSa#} {%der 4te Theil%} &lt;ls&gt;AK. 3,4,92.&lt;/ls&gt; {#aMSo &apos;zwamo &apos;hniH#} {%der 8te Abschnitt, die%} [Page1-0004] {%8te Stunde des%} (15stündigen) {%Tages%} &lt;ls&gt;AK. 2,7,31.&lt;/ls&gt; {#zazWamaMSaM pradadyAtpEtfkAdDanAt#} {%den 6ten Theil gebe er vom väterlichen Vermögen%} &lt;ls&gt;M. 9,164.&lt;/ls&gt; {#mamEvAMSaH#} {%ein Theil von mir%} &lt;ls&gt;BHAG. 15,7.&lt;/ls&gt; &lt;div n=&quot;2&quot;&gt;— b) {%ein Theil des Kaufpreises, Haftgeld%}: {#A na\stuja^M ra\yiM Ba\rAMSa\M na pra^tijAna\te#} &lt;ls&gt;ṚV. 3,45,4.&lt;/ls&gt; &lt;div n=&quot;2&quot;&gt;— c) {%Antheil%}: {#udinnva^sya ricyate\ aMSo\ Dana\M na ji\gyuza^H#} &lt;ls&gt;ṚV. 7,32,12.&lt;/ls&gt; {#aDA^yi DI\tirasa^sfgra\maMSA^H#} &lt;ls n=&quot;ṚV.&quot;&gt;10,31,3.&lt;/ls&gt; &lt;ls&gt;AV. 11,1,5.&lt;/ls&gt; {#taddAsEreva dAtavyaM svatoM &apos;SataH#} &lt;ls&gt;M. 8,408.&lt;/ls&gt; {%Erbschaftsantheil%}: {#anaMSO klIvapatitO#} &lt;ls&gt;M. 9,201.&lt;/ls&gt; {#niraMSaka#} {%ohne Erbtheil bleibend%} &lt;ls&gt;YĀJÑ. 2,140.&lt;/ls&gt; {#patnyaH kAryAH samAMSikAH#} &lt;ls n=&quot;YĀJÑ.&quot;&gt;2,115.&lt;/ls&gt; &lt;div n=&quot;2&quot;&gt;— d) {%Partei%}: {#a\smAka\maMSa\muda^vA\ Bare^ Bare#} &lt;ls&gt;ṚV. 1,102,4.&lt;/ls&gt; &lt;ls n=&quot;ṚV. 1,&quot;&gt;112,1.&lt;/ls&gt; &lt;div n=&quot;2&quot;&gt;— e) {%Nenner eines Bruchs%} &lt;ls&gt;COLEBR. Alg. 13.&lt;/ls&gt; &lt;div n=&quot;1&quot;&gt;— 2) {%Theilung, Erbschaftstheilung%} &lt;ls&gt;H. an. 2,542.&lt;/ls&gt; {#(viBAjane): sakfda ... [truncated]</note>
  <note type="source" target="pwk">&lt;L&gt;6&lt;pc&gt;1-001-a&lt;k1&gt;aMSa&lt;k2&gt;a/MSa {#a/MSa#}¦ &lt;lex&gt;m.&lt;/lex&gt; &lt;div n=&quot;1&quot;&gt;— 1〉 {%Theil:%} {#svAMSatas#} &lt;ls n=&quot;Chr.&quot;&gt;139,1&lt;/ls&gt;. &lt;div n=&quot;1&quot;&gt;— 2〉 {%Antheil, Erbtheil%}. &lt;div n=&quot;1&quot;&gt;— 3〉 {%Einsatz bei Wetten%} &lt;ls&gt;ṚV. 5,86,5&lt;/ls&gt;. &lt;ls&gt;TĀṆḌYA-BR. 25,13,3&lt;/ls&gt;. &lt;div n=&quot;1&quot;&gt;— 4〉 {%Partei%}. &lt;div n=&quot;1&quot;&gt;— 5〉 {%Grad eines Kreises%}. &lt;div n=&quot;1&quot;&gt;— 6〉 *{%Tag%} &lt;ls&gt;GAL.&lt;/ls&gt; &lt;div n=&quot;1&quot;&gt;— 7〉 &lt;ab&gt;N. pr.&lt;/ab&gt; eines &lt;is&gt;Āditya&lt;/is&gt;. &lt;LEND&gt;</note>
  <note type="curation">Human-reviewed and manually refined.</note>
</entry>
